pydplyr/__init__.py
pydplyr/arrange.py
pydplyr/filter.py
pydplyr/mutate.py
pydplyr/select.py
pydplyr/summarize.py
tests/01_test.py
tests/__init__.py
pydplyr-0.1.dist-info/LICENSE.txt
pydplyr-0.1.dist-info/METADATA
pydplyr-0.1.dist-info/WHEEL
pydplyr-0.1.dist-info/top_level.txt
pydplyr-0.1.dist-info/RECORD
