Metadata-Version: 2.1
Name: pydplyr
Version: 0.1
Summary: Syntax of dplyr in Python
Home-page: https://github.com/nabin2004/pydplyr
Author: Nabin Oli
Author-email: nabinoli2004@gmail.com
Classifier: Programming Language :: Python
Requires-Python: >=3.6
License-File: LICENSE.txt
